<annotation>
	<folder>batch10</folder>
	<filename>484.jpg</filename>
	<path>C:\Users\jazro\Downloads\batch10-20210612T190126Z-001\batch10\484.jpg</path>
	<source>
		<database>Unknown</database>
	</source>
	<size>
		<width>640</width>
		<height>360</height>
		<depth>3</depth>
	</size>
	<segmented>0</segmented>
	<object>
		<name>armor</name>
		<pose>Unspecified</pose>
		<truncated>0</truncated>
		<difficult>0</difficult>
		<bndbox>
			<xmin>71</xmin>
			<ymin>199</ymin>
			<xmax>114</xmax>
			<ymax>223</ymax>
		</bndbox>
	</object>
	<object>
		<name>armor</name>
		<pose>Unspecified</pose>
		<truncated>0</truncated>
		<difficult>0</difficult>
		<bndbox>
			<xmin>152</xmin>
			<ymin>179</ymin>
			<xmax>167</xmax>
			<ymax>202</ymax>
		</bndbox>
	</object>
	<object>
		<name>armor</name>
		<pose>Unspecified</pose>
		<truncated>0</truncated>
		<difficult>0</difficult>
		<bndbox>
			<xmin>198</xmin>
			<ymin>219</ymin>
			<xmax>222</xmax>
			<ymax>237</ymax>
		</bndbox>
	</object>
	<object>
		<name>armor</name>
		<pose>Unspecified</pose>
		<truncated>0</truncated>
		<difficult>0</difficult>
		<bndbox>
			<xmin>291</xmin>
			<ymin>200</ymin>
			<xmax>316</xmax>
			<ymax>218</ymax>
		</bndbox>
	</object>
	<object>
		<name>armor</name>
		<pose>Unspecified</pose>
		<truncated>0</truncated>
		<difficult>0</difficult>
		<bndbox>
			<xmin>226</xmin>
			<ymin>121</ymin>
			<xmax>255</xmax>
			<ymax>141</ymax>
		</bndbox>
	</object>
	<object>
		<name>armor</name>
		<pose>Unspecified</pose>
		<truncated>0</truncated>
		<difficult>0</difficult>
		<bndbox>
			<xmin>295</xmin>
			<ymin>121</ymin>
			<xmax>318</xmax>
			<ymax>140</ymax>
		</bndbox>
	</object>
	<object>
		<name>armor</name>
		<pose>Unspecified</pose>
		<truncated>0</truncated>
		<difficult>0</difficult>
		<bndbox>
			<xmin>444</xmin>
			<ymin>149</ymin>
			<xmax>456</xmax>
			<ymax>169</ymax>
		</bndbox>
	</object>
	<object>
		<name>armor</name>
		<pose>Unspecified</pose>
		<truncated>0</truncated>
		<difficult>0</difficult>
		<bndbox>
			<xmin>504</xmin>
			<ymin>160</ymin>
			<xmax>525</xmax>
			<ymax>175</ymax>
		</bndbox>
	</object>
</annotation>
